README.md
setup.py
magniv/__init__.py
magniv.egg-info/PKG-INFO
magniv.egg-info/SOURCES.txt
magniv.egg-info/dependency_links.txt
magniv.egg-info/entry_points.txt
magniv.egg-info/requires.txt
magniv.egg-info/top_level.txt
magniv/build/__init__.py
magniv/build/build.py
magniv/core/__init__.py
magniv/core/task.py
magniv/export/__init__.py
magniv/export/export.py
magniv/export/airflow/__init__.py
magniv/export/airflow/dag-template.py
magniv/export/airflow/export_to_airflow.py
magniv/run/__init__.py
magniv/run/run.py
magniv/scripts/__init__.py
magniv/scripts/magniv.py
magniv/utils/__init__.py
magniv/utils/utils.py
tests/__init__.py
tests/unit_tests/__init__.py
tests/unit_tests/test_build.py
tests/unit_tests/test_build_imports.py
tests/unit_tests/test_invalid_call.py
tests/unit_tests/test_invalid_kwarg.py
tests/unit_tests/test_invalid_trigger.py