Metadata-Version: 1.2
Name: magniv
Version: 0.1.51
Summary: Magniv Core Library
Home-page: https://www.magniv.io
Author-email: hello@magniv.io
License: UNKNOWN
Project-URL: Documentation, https://docs.magniv.io
Platform: UNKNOWN
